pyresizer/__init__.py
pyresizer/__main__.py
pyresizer/constants.py
pyresizer/gui.py
pyresizer/image.py
PyResizer-0.1.2.dist-info/AUTHORS
PyResizer-0.1.2.dist-info/LICENSE
PyResizer-0.1.2.dist-info/METADATA
PyResizer-0.1.2.dist-info/WHEEL
PyResizer-0.1.2.dist-info/entry_points.txt
PyResizer-0.1.2.dist-info/top_level.txt
PyResizer-0.1.2.dist-info/RECORD
