Metadata-Version: 2.1
Name: PyResizer
Version: 0.1.2
Summary: Tkinter GUI program to resize images via pillow
Home-page: https://github.com/jedie/PyResizer
Author: Jens Diemer
Author-email: pypi@jensdiemer.de
License: UNKNOWN
Platform: UNKNOWN
Classifier: Programming Language :: Python :: 3
Classifier: License :: OSI Approved :: GNU General Public License v3 or later (GPLv3+)
Classifier: Operating System :: OS Independent
Requires-Python: >=3.5
Requires-Dist: pillow
